dfu/__init__.py
dfu/astutils.py
dfu/messages.py
dfu/pylint.py
dfu/sp.py
dfu/flake8/__init__.py
dfu/flake8/check.py
dfu/flake8/lib.py
dfu/flake8/pep263.py
dont_fudge_up-0.0.6.dist-info/DESCRIPTION.rst
dont_fudge_up-0.0.6.dist-info/METADATA
dont_fudge_up-0.0.6.dist-info/RECORD
dont_fudge_up-0.0.6.dist-info/WHEEL
dont_fudge_up-0.0.6.dist-info/entry_points.txt
dont_fudge_up-0.0.6.dist-info/metadata.json
dont_fudge_up-0.0.6.dist-info/top_level.txt
dont_fudge_up-0.0.6.dist-info/zip-safe
