Metadata-Version: 2.0
Name: dont-fudge-up
Version: 0.0.6
Summary: Find operations that might fudge up production, like a pdb.set_trace
Home-page: https://github.com/NorthIsUp/dont-fudge-up
Author: Adam Hitchcock
Author-email: adam@disqus.com
License: BSD
Platform: UNKNOWN
Classifier: Intended Audience :: Developers
Classifier: License :: OSI Approved :: BSD License
Classifier: Operating System :: OS Independent
Classifier: Topic :: Software Development
Classifier: Programming Language :: Python
Classifier: Programming Language :: Python :: 2
Classifier: Programming Language :: Python :: 2.7
Classifier: Programming Language :: Python :: 3
Provides-Extra: tests
Requires-Dist: flake8; extra == 'tests'
